ipyvizzu-0.18.0.dist-info/METADATA
ipyvizzu-0.18.0.dist-info/WHEEL
ipyvizzu-0.18.0.dist-info/entry_points.txt
ipyvizzu-0.18.0.dist-info/licenses/LICENSE
ipyvizzu/__init__.py
ipyvizzu/__version__.py
ipyvizzu/animation.py
ipyvizzu/animationcontrol.py
ipyvizzu/chart.py
ipyvizzu/data/__init__.py
ipyvizzu/data/converters/__init__.py
ipyvizzu/data/converters/converter.py
ipyvizzu/data/converters/defaults.py
ipyvizzu/data/converters/df/__init__.py
ipyvizzu/data/converters/df/converter.py
ipyvizzu/data/converters/df/defaults.py
ipyvizzu/data/converters/df/type_alias.py
ipyvizzu/data/converters/numpy/__init__.py
ipyvizzu/data/converters/numpy/converter.py
ipyvizzu/data/converters/numpy/type_alias.py
ipyvizzu/data/converters/pandas/__init__.py
ipyvizzu/data/converters/pandas/converter.py
ipyvizzu/data/converters/pandas/protocol.py
ipyvizzu/data/converters/spark/__init__.py
ipyvizzu/data/converters/spark/converter.py
ipyvizzu/data/converters/spark/protocol.py
ipyvizzu/data/infer_type.py
ipyvizzu/data/type_alias.py
ipyvizzu/event.py
ipyvizzu/integrations/__init__.py
ipyvizzu/integrations/fugue.py
ipyvizzu/json.py
ipyvizzu/method.py
ipyvizzu/py.typed
ipyvizzu/schema.py
ipyvizzu/template.py
ipyvizzu/templates/ipyvizzu.js
ipyvizzu-0.18.0.dist-info/RECORD
