Metadata-Version: 2.1
Name: ipyvizzu
Version: 0.18.0
Summary: Build animated charts in Jupyter Notebook and similar environments with a simple Python syntax.
Keywords: python,chart,charts,dataviz,jupyter,animation,ipython,graphs,storytelling,jupyter-notebook,data-visualization,graphing,plotting,charting,vizzu
Author-Email: "Vizzu Inc." <hello@vizzu.io>
License: Apache-2.0
Classifier: Environment :: Console
Classifier: License :: OSI Approved :: Apache Software License
Classifier: Operating System :: OS Independent
Classifier: Programming Language :: Python :: 3
Project-URL: Homepage, https://ipyvizzu.vizzuhq.com
Project-URL: Documentation, https://ipyvizzu.vizzuhq.com
Project-URL: Source, https://github.com/vizzuhq/ipyvizzu
Project-URL: Tracker, https://github.com/vizzuhq/ipyvizzu/issues
Requires-Python: >=3.9
Requires-Dist: IPython
Requires-Dist: jsonschema
Provides-Extra: pandas
Requires-Dist: pandas; extra == "pandas"
Provides-Extra: pyspark
Requires-Dist: pyspark; extra == "pyspark"
Provides-Extra: numpy
Requires-Dist: numpy; extra == "numpy"
Provides-Extra: fugue
Requires-Dist: fugue[sql]; extra == "fugue"
